bquant/__init__.py
bquant/cli.py
bquant/analysis/__init__.py
bquant/analysis/candlestick/__init__.py
bquant/analysis/chart/__init__.py
bquant/analysis/statistical/__init__.py
bquant/analysis/statistical/hypothesis_testing.py
bquant/analysis/technical/__init__.py
bquant/analysis/timeseries/__init__.py
bquant/analysis/zones/__init__.py
bquant/analysis/zones/sequence_analysis.py
bquant/analysis/zones/zone_features.py
bquant/core/__init__.py
bquant/core/cache.py
bquant/core/config.py
bquant/core/exceptions.py
bquant/core/logging_config.py
bquant/core/numpy_fix.py
bquant/core/performance.py
bquant/core/utils.py
bquant/data/__init__.py
bquant/data/loader.py
bquant/data/processor.py
bquant/data/schemas.py
bquant/data/validator.py
bquant/data/samples/__init__.py
bquant/data/samples/datasets.py
bquant/data/samples/utils.py
bquant/data/samples/embedded/__init__.py
bquant/data/samples/embedded/mt_xauusd_m15.py
bquant/data/samples/embedded/tv_xauusd_1h.py
bquant/indicators/__init__.py
bquant/indicators/base.py
bquant/indicators/calculators.py
bquant/indicators/library.py
bquant/indicators/loaders.py
bquant/indicators/macd.py
bquant/ml/__init__.py
bquant/visualization/__init__.py
bquant/visualization/charts.py
bquant/visualization/statistical.py
bquant/visualization/themes.py
bquant/visualization/zones.py
bquant-0.0.0.dist-info/licenses/LICENSE
bquant-0.0.0.dist-info/METADATA
bquant-0.0.0.dist-info/WHEEL
bquant-0.0.0.dist-info/entry_points.txt
bquant-0.0.0.dist-info/top_level.txt
bquant-0.0.0.dist-info/RECORD
