Metadata-Version: 2.4
Name: bquant
Version: 0.0.0
Summary: Quantitative research toolkit for financial markets
Author-email: kogriv <kogriv@gmail.com>
License: MIT
Project-URL: Homepage, https://github.com/kogriv/bquant
Project-URL: Documentation, https://bquant.readthedocs.io/
Project-URL: Repository, https://github.com/kogriv/bquant.git
Project-URL: Issues, https://github.com/kogriv/bquant/issues
Classifier: Development Status :: 4 - Beta
Classifier: Intended Audience :: Financial and Insurance Industry
Classifier: License :: OSI Approved :: MIT License
Classifier: Operating System :: OS Independent
Classifier: Programming Language :: Python :: 3.13
Classifier: Topic :: Office/Business :: Financial
Classifier: Topic :: Scientific/Engineering :: Information Analysis
Requires-Python: >=3.13
License-File: LICENSE
Requires-Dist: pandas==2.3.1
Requires-Dist: numpy==2.3.2
Requires-Dist: matplotlib==3.10.5
Requires-Dist: seaborn==0.13.2
Requires-Dist: pandas-ta==0.3.14b0
Requires-Dist: statsmodels==0.14.5
Requires-Dist: scipy==1.16.1
Requires-Dist: scikit-learn==1.7.1
Requires-Dist: plotly==6.3.0
Requires-Dist: kaleido==1.0.0
Requires-Dist: ipywidgets==8.1.7
Requires-Dist: psutil>=5.9.0
Provides-Extra: dev
Requires-Dist: pytest>=6.0; extra == "dev"
Requires-Dist: pytest-cov>=2.0; extra == "dev"
Requires-Dist: black>=21.0; extra == "dev"
Requires-Dist: flake8>=3.8; extra == "dev"
Provides-Extra: notebooks
Requires-Dist: jupyter==1.1.1; extra == "notebooks"
Requires-Dist: ipywidgets==8.1.7; extra == "notebooks"
Requires-Dist: plotly==6.3.0; extra == "notebooks"
Requires-Dist: kaleido==1.0.0; extra == "notebooks"
Provides-Extra: full
Requires-Dist: pytest>=6.0; extra == "full"
Requires-Dist: pytest-cov>=2.0; extra == "full"
Requires-Dist: black>=21.0; extra == "full"
Requires-Dist: flake8>=3.8; extra == "full"
Requires-Dist: jupyter==1.1.1; extra == "full"
Requires-Dist: ipywidgets==8.1.7; extra == "full"
Requires-Dist: plotly==6.3.0; extra == "full"
Requires-Dist: kaleido==1.0.0; extra == "full"
Dynamic: license-file
